pydoll_mcp/__init__.py
pydoll_mcp/__main__.py
pydoll_mcp/browser_manager.py
pydoll_mcp/cli.py
pydoll_mcp/server.py
pydoll_mcp/models/__init__.py
pydoll_mcp/tools/__init__.py
pydoll_mcp/tools/advanced_tools.py
pydoll_mcp/tools/browser_tools.py
pydoll_mcp/tools/element_tools.py
pydoll_mcp/tools/navigation_tools.py
pydoll_mcp/tools/screenshot_tools.py
pydoll_mcp/tools/script_tools.py
pydoll_mcp-1.1.3.dist-info/licenses/LICENSE
pydoll_mcp-1.1.3.dist-info/METADATA
pydoll_mcp-1.1.3.dist-info/WHEEL
pydoll_mcp-1.1.3.dist-info/entry_points.txt
pydoll_mcp-1.1.3.dist-info/top_level.txt
pydoll_mcp-1.1.3.dist-info/RECORD
