Metadata-Version: 2.4
Name: pydoll-mcp
Version: 1.1.3
Summary: Revolutionary Model Context Protocol (MCP) server for PyDoll browser automation with zero-webdriver operation and intelligent captcha bypass
Home-page: https://github.com/JinsongRoh/pydoll-mcp
Author: Jinsong Roh
Author-email: Jinsong Roh <jinsongroh@gmail.com>
Maintainer-email: Jinsong Roh <jinsongroh@gmail.com>
License: MIT License
Project-URL: Homepage, https://github.com/JinsongRoh/pydoll-mcp
Project-URL: Repository, https://github.com/JinsongRoh/pydoll-mcp.git
Project-URL: Documentation, https://github.com/JinsongRoh/pydoll-mcp/wiki
Project-URL: Bug Tracker, https://github.com/JinsongRoh/pydoll-mcp/issues
Project-URL: Changelog, https://github.com/JinsongRoh/pydoll-mcp/blob/main/CHANGELOG.md
Project-URL: Discussions, https://github.com/JinsongRoh/pydoll-mcp/discussions
Project-URL: Sponsor, https://github.com/sponsors/JinsongRoh
Keywords: mcp,browser-automation,web-scraping,captcha-bypass,claude,ai,automation,testing,selenium-alternative,cloudflare,recaptcha,anti-detection,stealth
Classifier: Development Status :: 4 - Beta
Classifier: Intended Audience :: Developers
Classifier: Intended Audience :: System Administrators
Classifier: License :: OSI Approved :: MIT License
Classifier: Operating System :: OS Independent
Classifier: Programming Language :: Python :: 3
Classifier: Programming Language :: Python :: 3.8
Classifier: Programming Language :: Python :: 3.9
Classifier: Programming Language :: Python :: 3.10
Classifier: Programming Language :: Python :: 3.11
Classifier: Programming Language :: Python :: 3.12
Classifier: Topic :: Internet :: WWW/HTTP :: Browsers
Classifier: Topic :: Software Development :: Testing
Classifier: Topic :: Software Development :: Libraries :: Python Modules
Classifier: Topic :: System :: Networking
Classifier: Environment :: Console
Classifier: Framework :: AsyncIO
Requires-Python: >=3.8
License-File: LICENSE
Requires-Dist: pydoll-python>=2.2.0
Requires-Dist: mcp>=1.0.0
Requires-Dist: pydantic>=2.0.0
Requires-Dist: typing-extensions>=4.0.0
Requires-Dist: asyncio-throttle>=1.0.0
Requires-Dist: aiofiles>=23.0.0
Requires-Dist: python-dotenv>=1.0.0
Requires-Dist: rich>=13.0.0
Requires-Dist: click>=8.0.0
Provides-Extra: dev
Requires-Dist: pytest>=7.0.0; extra == "dev"
Requires-Dist: pytest-asyncio>=0.21.0; extra == "dev"
Requires-Dist: pytest-cov>=4.0.0; extra == "dev"
Requires-Dist: black>=23.0.0; extra == "dev"
Requires-Dist: ruff>=0.1.0; extra == "dev"
Requires-Dist: mypy>=1.0.0; extra == "dev"
Requires-Dist: pre-commit>=3.0.0; extra == "dev"
Requires-Dist: coverage[toml]>=7.0.0; extra == "dev"
Provides-Extra: test
Requires-Dist: pytest>=7.0.0; extra == "test"
Requires-Dist: pytest-asyncio>=0.21.0; extra == "test"
Requires-Dist: pytest-cov>=4.0.0; extra == "test"
Requires-Dist: aioresponses>=0.7.0; extra == "test"
Provides-Extra: docs
Requires-Dist: mkdocs>=1.5.0; extra == "docs"
Requires-Dist: mkdocs-material>=9.0.0; extra == "docs"
Requires-Dist: mkdocstrings[python]>=0.24.0; extra == "docs"
Provides-Extra: all
Requires-Dist: pydoll-mcp[dev,docs,test]; extra == "all"
Dynamic: author
Dynamic: home-page
Dynamic: license-file
Dynamic: requires-python
